devpi_findlinks/__init__.py
devpi_findlinks/main.py
devpi_findlinks-3.0.1.dist-info/METADATA
devpi_findlinks-3.0.1.dist-info/WHEEL
devpi_findlinks-3.0.1.dist-info/entry_points.txt
devpi_findlinks-3.0.1.dist-info/top_level.txt
devpi_findlinks-3.0.1.dist-info/RECORD
