Metadata-Version: 2.1
Name: devpi-findlinks
Version: 3.0.1
Summary: devpi-findlinks: find-links view for devpi-server
Home-page: https://github.com/devpi/devpi-findlinks
Maintainer: Florian Schulze
Maintainer-email: florian.schulze@gmx.net
License: MIT
Classifier: Environment :: Web Environment
Classifier: Intended Audience :: Developers
Classifier: Intended Audience :: System Administrators
Classifier: License :: OSI Approved :: MIT License
Classifier: Programming Language :: Python
Classifier: Programming Language :: Python :: 3
Classifier: Programming Language :: Python :: 3.8
Classifier: Programming Language :: Python :: 3.9
Classifier: Programming Language :: Python :: 3.10
Classifier: Programming Language :: Python :: 3.11
Classifier: Programming Language :: Python :: 3.12
Requires-Python: >=3.8
Requires-Dist: devpi-server >=5.2.0
